calixa_proto_py/__init__.py
calixa_proto_py/account.proto
calixa_proto_py/account_pb2.py
calixa_proto_py/account_pb2.pyi
calixa_proto_py/account_pb2_grpc.py
calixa_proto_py/action.proto
calixa_proto_py/action_pb2.py
calixa_proto_py/action_pb2.pyi
calixa_proto_py/action_pb2_grpc.py
calixa_proto_py/action_service.proto
calixa_proto_py/action_service_pb2.py
calixa_proto_py/action_service_pb2.pyi
calixa_proto_py/action_service_pb2_grpc.py
calixa_proto_py/audience.proto
calixa_proto_py/audience_pb2.py
calixa_proto_py/audience_pb2.pyi
calixa_proto_py/audience_pb2_grpc.py
calixa_proto_py/audience_sync.proto
calixa_proto_py/audience_sync_pb2.py
calixa_proto_py/audience_sync_pb2.pyi
calixa_proto_py/audience_sync_pb2_grpc.py
calixa_proto_py/authentication.proto
calixa_proto_py/authentication_pb2.py
calixa_proto_py/authentication_pb2.pyi
calixa_proto_py/authentication_pb2_grpc.py
calixa_proto_py/automation.proto
calixa_proto_py/automation_log.proto
calixa_proto_py/automation_log_pb2.py
calixa_proto_py/automation_log_pb2.pyi
calixa_proto_py/automation_log_pb2_grpc.py
calixa_proto_py/automation_pb2.py
calixa_proto_py/automation_pb2.pyi
calixa_proto_py/automation_pb2_grpc.py
calixa_proto_py/automation_service.proto
calixa_proto_py/automation_service_pb2.py
calixa_proto_py/automation_service_pb2.pyi
calixa_proto_py/automation_service_pb2_grpc.py
calixa_proto_py/billing.proto
calixa_proto_py/billing_pb2.py
calixa_proto_py/billing_pb2.pyi
calixa_proto_py/billing_pb2_grpc.py
calixa_proto_py/collaboration.proto
calixa_proto_py/collaboration_entity.proto
calixa_proto_py/collaboration_entity_pb2.py
calixa_proto_py/collaboration_entity_pb2.pyi
calixa_proto_py/collaboration_entity_pb2_grpc.py
calixa_proto_py/collaboration_pb2.py
calixa_proto_py/collaboration_pb2.pyi
calixa_proto_py/collaboration_pb2_grpc.py
calixa_proto_py/common.proto
calixa_proto_py/common_pb2.py
calixa_proto_py/common_pb2.pyi
calixa_proto_py/common_pb2_grpc.py
calixa_proto_py/condition.proto
calixa_proto_py-2.0.38.dist-info/METADATA
calixa_proto_py-2.0.38.dist-info/WHEEL
calixa_proto_py-2.0.38.dist-info/entry_points.txt
calixa_proto_py-2.0.38.dist-info/RECORD
