Metadata-Version: 2.1
Name: calixa-proto-py
Version: 2.0.38
Summary: Calixa proto py
Author: Calixa Platform Developers
Author-email: everyone@calixa.io
Requires-Python: >=3.7,<4.0
Classifier: Programming Language :: Python :: 3
Classifier: Programming Language :: Python :: 3.7
Classifier: Programming Language :: Python :: 3.8
Classifier: Programming Language :: Python :: 3.9
Classifier: Programming Language :: Python :: 3.10
Classifier: Programming Language :: Python :: 3.11
Requires-Dist: googleapis-common-protos (>=1.52,<2.0)
Requires-Dist: grpcio-tools (>=1.30,<2.0)
Requires-Dist: mypy-protobuf (>=1.23,<2.0)
